{"committer_email": "ch3cooli@gmail.com", "short_id": "bf9e81c6", "title": "Initialize libgit before using mailmap", "author_email": "email@cs-ware.de", "authored_date": "2020-03-18T18:04:21.000+01:00", "created_at": "2020-03-19T21:20:59.000+08:00", "author_name": "Sven Strickroth", "web_url": "https://gitlab.com/abhinavbajpai2012/tortoisegit/-/commit/bf9e81c62734b544684a4494c8c9fd634753646d", "parent_ids_0": "18def0ddfb8d0b3d087e92484cf6d94633f0a9b8", "committed_date": "2020-03-19T21:20:59.000+08:00", "message": "Initialize libgit before using mailmap\n\nSigned-off-by: Sven Strickroth <email@cs-ware.de>\n", "committer_name": "Sup Yut Sum", "id": "bf9e81c62734b544684a4494c8c9fd634753646d"}